examples/batch_processing.py
examples/complex_workflow.py
examples/failing_flow.py
examples/media_pipeline.py
examples/parallel_scraper.py
examples/saga_trip_booking.py
examples/simple_flow.py
senpuki/__init__.py
senpuki/cli.py
senpuki/core.py
senpuki/executor.py
senpuki/metrics.py
senpuki/registry.py
senpuki/telemetry.py
senpuki/backend/__init__.py
senpuki/backend/base.py
senpuki/backend/postgres.py
senpuki/backend/sqlite.py
senpuki/backend/utils.py
senpuki/notifications/__init__.py
senpuki/notifications/base.py
senpuki/notifications/redis.py
senpuki/utils/__init__.py
senpuki/utils/async_sqlite.py
senpuki/utils/idempotency.py
senpuki/utils/serialization.py
senpuki/utils/time.py
tests/__init__.py
tests/test_backend_correctness.py
tests/test_core.py
tests/test_deadlock.py
tests/test_execution.py
tests/test_helpers.py
tests/test_map.py
tests/test_max_duration.py
tests/test_parallel.py
tests/test_rate_limit.py
tests/test_scenarios.py
tests/test_scheduling.py
tests/test_signals.py
tests/test_wait_for.py
tests/utils.py
senpuki-0.2.0.dist-info/METADATA
senpuki-0.2.0.dist-info/WHEEL
senpuki-0.2.0.dist-info/entry_points.txt
senpuki-0.2.0.dist-info/top_level.txt
senpuki-0.2.0.dist-info/RECORD
