Metadata-Version: 2.4
Name: senpuki
Version: 0.2.0
Summary: Distributed Durable Functions in Python
Author-email: noku <noku@onlypa.ws>
Project-URL: Homepage, https://github.com/nokusukun/senpuki
Project-URL: Issues, https://github.com/nokusukun/senpuki/issues
Requires-Python: >=3.12
Requires-Dist: aiosqlite>=0.21.0
Requires-Dist: asyncpg>=0.31.0
Requires-Dist: pyrefly>=0.43.1
Requires-Dist: redis>=7.1.0
